blazar/__init__.py
blazar/config.py
blazar/context.py
blazar/exceptions.py
blazar/i18n.py
blazar/opts.py
blazar/policy.py
blazar/rpc.py
blazar/status.py
blazar/version.py
blazar/api/__init__.py
blazar/api/app.py
blazar/api/context.py
blazar/api/root.py
blazar/api/wsgi_app.py
blazar/api/v1/__init__.py
blazar/api/v1/api_version_request.py
blazar/api/v1/app.py
blazar/api/v1/request_id.py
blazar/api/v1/request_log.py
blazar/api/v1/rest_api_version_history.rst
blazar/api/v1/utils.py
blazar/api/v1/validation.py
blazar/api/v1/floatingips/__init__.py
blazar/api/v1/floatingips/service.py
blazar/api/v1/floatingips/v1_0.py
blazar/api/v1/leases/__init__.py
blazar/api/v1/leases/service.py
blazar/api/v1/leases/v1_0.py
blazar/api/v1/oshosts/__init__.py
blazar/api/v1/oshosts/service.py
blazar/api/v1/oshosts/v1_0.py
blazar/api/v2/__init__.py
blazar/api/v2/app.py
blazar/api/v2/hooks.py
blazar/api/v2/controllers/__init__.py
blazar/api/v2/controllers/base.py
blazar/api/v2/controllers/types.py
blazar/api/v2/controllers/extensions/__init__.py
blazar/api/v2/controllers/extensions/host.py
blazar/api/v2/controllers/extensions/lease.py
blazar/api/v2/middleware/__init__.py
blazar/cmd/__init__.py
blazar/cmd/api.py
blazar/cmd/manager.py
blazar/cmd/status.py
blazar/db/__init__.py
blazar/db/api.py
blazar/db/base.py
blazar/db/exceptions.py
blazar/db/utils.py
blazar/db/migration/README
blazar/db/migration/__init__.py
blazar/db/migration/alembic.ini
blazar/db/migration/cli.py
blazar/db/migration/alembic_migrations/env.py
blazar/db/migration/alembic_migrations/script.py.mako
blazar/db/migration/alembic_migrations/versions/02e2f2186d98_resource_property.py
blazar/db/migration/alembic_migrations/versions/0_1_initial.py
blazar/db/migration/alembic_migrations/versions/10e34bba18e8_add_service_name_to_.py
blazar/db/migration/alembic_migrations/versions/1fd6c2eded89_add_trust_id_to_comp.py
blazar/db/migration/alembic_migrations/versions/23d6240b51b2_add_status_to_leases.py
blazar-16.0.0.dist-info/AUTHORS
blazar-16.0.0.dist-info/LICENSE
blazar-16.0.0.dist-info/METADATA
blazar-16.0.0.dist-info/WHEEL
blazar-16.0.0.dist-info/entry_points.txt
blazar-16.0.0.dist-info/pbr.json
blazar-16.0.0.dist-info/top_level.txt
blazar-16.0.0.dist-info/RECORD
